{
  "main": {
    "id": "0d9e3f5ee91caf85",
    "type": "split",
    "children": [
      {
        "id": "3024828216b1cfdd",
        "type": "tabs",
        "children": [
          {
            "id": "a053de4e011fadfc",
            "type": "leaf",
            "state": {
              "type": "pdf-annotator",
              "state": {
                "file": "annotation/2009_thinkingInSystems_donella.md"
              },
              "icon": "lucide-file",
              "title": "2009_thinkingInSystems_donella"
            }
          }
        ]
      }
    ],
    "direction": "vertical"
  },
  "left": {
    "id": "0e0a4037320cb370",
    "type": "split",
    "children": [
      {
        "id": "a8cd255e1480a5f8",
        "type": "tabs",
        "children": [
          {
            "id": "d3d76f581020f965",
            "type": "leaf",
            "state": {
              "type": "file-explorer",
              "state": {
                "sortOrder": "alphabetical",
                "autoReveal": true
              },
              "icon": "lucide-folder-closed",
              "title": "Files"
            }
          },
          {
            "id": "67fc5c9d36728747",
            "type": "leaf",
            "state": {
              "type": "search",
              "state": {
                "query": "",
                "matchingCase": false,
                "explainSearch": false,
                "collapseAll": false,
                "extraContext": false,
                "sortOrder": "alphabetical"
              },
              "icon": "lucide-search",
              "title": "Search"
            }
          },
          {
            "id": "588820ee7da89fa4",
            "type": "leaf",
            "state": {
              "type": "bookmarks",
              "state": {},
              "icon": "lucide-bookmark",
              "title": "Bookmarks"
            }
          }
        ]
      }
    ],
    "direction": "horizontal",
    "width": 200
  },
  "right": {
    "id": "1f2272b957ad87f8",
    "type": "split",
    "children": [
      {
        "id": "1969e07d7cd7b385",
        "type": "tabs",
        "children": [
          {
            "id": "09b67525e980c91c",
            "type": "leaf",
            "state": {
              "type": "backlink",
              "state": {
                "file": "Fundamentals.md",
                "collapseAll": false,
                "extraContext": false,
                "sortOrder": "alphabetical",
                "showSearch": false,
                "searchQuery": "",
                "backlinkCollapsed": false,
                "unlinkedCollapsed": true
              },
              "icon": "links-coming-in",
              "title": "Backlinks for Fundamentals"
            }
          },
          {
            "id": "1ae3216b03ad150d",
            "type": "leaf",
            "state": {
              "type": "outgoing-link",
              "state": {
                "file": "Fundamentals.md",
                "linksCollapsed": false,
                "unlinkedCollapsed": true
              },
              "icon": "links-going-out",
              "title": "Outgoing links from Fundamentals"
            }
          },
          {
            "id": "490729e2d8d9b997",
            "type": "leaf",
            "state": {
              "type": "tag",
              "state": {
                "sortOrder": "frequency",
                "useHierarchy": true,
                "showSearch": false,
                "searchQuery": ""
              },
              "icon": "lucide-tags",
              "title": "Tags"
            }
          },
          {
            "id": "78359b74b35cd5b5",
            "type": "leaf",
            "state": {
              "type": "all-properties",
              "state": {
                "sortOrder": "frequency",
                "showSearch": false,
                "searchQuery": ""
              },
              "icon": "lucide-archive",
              "title": "All properties"
            }
          },
          {
            "id": "cbdb3198274d9a03",
            "type": "leaf",
            "state": {
              "type": "outline",
              "state": {
                "file": "Fundamentals.md",
                "followCursor": false,
                "showSearch": false,
                "searchQuery": ""
              },
              "icon": "lucide-list",
              "title": "Outline of Fundamentals"
            }
          }
        ],
        "currentTab": 4
      }
    ],
    "direction": "horizontal",
    "width": 219.5,
    "collapsed": true
  },
  "left-ribbon": {
    "hiddenItems": {
      "switcher:Open quick switcher": false,
      "graph:Open graph view": false,
      "canvas:Create new canvas": false,
      "daily-notes:Open today's daily note": false,
      "templates:Insert template": false,
      "command-palette:Open command palette": false,
      "bases:Create new base": false
    }
  },
  "active": "a053de4e011fadfc",
  "lastOpenFiles": [
    "annotation/2017_AN_forestMensuration_johnEtAll.md",
    "annotation/2009_thinkingInSystems_donella.md",
    "annotation/2019_AN_smallhoderFarmerCharacterizationTanzania_DevothaEtAll.md",
    "annotation/2020_AN_deepLearningRemoteSensing_remiCresson.md",
    "annotation/2021_AN_EarthObservation_rebekah.md",
    "annotation/2024_AN_ATBD_esaCCIV6.md",
    "annotation/2024_AN_speechLanguageProcessing_Daniel.md",
    "annotation/2025_AN_deforestationAmazon_DarcioEtAll.md",
    "annotation/2025_AN_geoAIHumanGeography_springer.md",
    "annotation/2025_AN_towardsGeoAI_genchenEtAll.md",
    "CNN.md",
    "2026-02-18.md",
    "basic_cnn.md",
    "stride.md",
    "Basic.md",
    "video/deep learning.md",
    "0 ebook.base",
    "models.md",
    "pytorch.md",
    "Fundamentals.md",
    "Pasted image 20260214202814.png",
    "Loss function.md",
    "**Train/Val/Test splits.md",
    "**Train/Val",
    "**Train",
    "Patch-based Classification.md",
    "Overfitting.md",
    "Data Preprocessing.md",
    "Transfer Learning.md",
    "Pretrained weights.md",
    "code/resource/scene_classification.tif",
    "code/resource/imageToDriveExample_transform.tif",
    "Pasted image 20260217221121.png",
    "Pasted image 20260217220940.png",
    "Pasted image 20260217220834.png",
    "code/resource",
    "code/untitled folder",
    "code/scene_classification_tutorial.ipynb",
    "code/pytorch (1).ipynb",
    "code/scene_classification.ipynb",
    "video/Pasted image 20260217220755.png",
    "video/Pasted image 20260217211222.png",
    "video/Pasted image 20260217205238.png",
    "Pasted image 20260217212101.png",
    "Untitled.canvas",
    "transformers/Pasted image 20260214083335.png",
    "change detection/Pasted image 20260213223858.png"
  ]
}